earthquake_detection/__init__.py
latest_indonesia_earthquake-0.3.dist-info/LICENSE
latest_indonesia_earthquake-0.3.dist-info/METADATA
latest_indonesia_earthquake-0.3.dist-info/WHEEL
latest_indonesia_earthquake-0.3.dist-info/top_level.txt
latest_indonesia_earthquake-0.3.dist-info/RECORD
