Metadata-Version: 2.1
Name: latest-indonesia-earthquake
Version: 0.3
Summary: Latest information Indonesia earthquake from Meteorological, Climatological, and Geophysical Agency
Home-page: https://github.com/Ade-Project/latest-indonesia-earthquake
Author: Ade Ristanto
Author-email: ade.ristanto@gmail.com
License: UNKNOWN
Project-URL: GitHub, https://github.com/AdeRistanto
Platform: UNKNOWN
Classifier: Programming Language :: Python :: 3
Classifier: License :: OSI Approved :: GNU General Public License v3 (GPLv3)
Classifier: Operating System :: OS Independent
Classifier: Development Status :: 5 - Production/Stable
Requires-Python: >=3.6
License-File: LICENSE
